mouse_jiggler/__init__.py
mouse_jiggler/jiggler.py
mouse_jiggler_macos-1.6.0.dist-info/METADATA
mouse_jiggler_macos-1.6.0.dist-info/WHEEL
mouse_jiggler_macos-1.6.0.dist-info/entry_points.txt
mouse_jiggler_macos-1.6.0.dist-info/top_level.txt
mouse_jiggler_macos-1.6.0.dist-info/RECORD
