Metadata-Version: 2.1
Name: mouse_jiggler_macos
Version: 1.6.0
Summary: A simple mouse jiggler for MacOS
Home-page: https://github.com/UmairK5669/mouse-jiggler
Author: Umair Khan
Author-email: u7khan@uwaterloo.ca
Classifier: Programming Language :: Python :: 3
Classifier: Operating System :: MacOS
Classifier: License :: OSI Approved :: MIT License
Requires-Python: >=3.6
Requires-Dist: pynput
Requires-Dist: pyautogui
Requires-Dist: pync
